pyilpp/__init__.py
pyilpp-0.1.0.dist-info/WHEEL
pyilpp-0.1.0.dist-info/METADATA
pyilpp-0.1.0.dist-info/licenses/LICENSE
pyilpp-0.1.0.dist-info/RECORD
