Metadata-Version: 2.1
Name: pyilpp
Version: 0.1.0
Summary: idb line protocol parser
License: MIT
Author-email: Maximiliano Curia <maxy@gnuservers.com.ar>
Requires-Python: >=3.11
Classifier: License :: OSI Approved :: MIT License
Classifier: Operating System :: OS Independent
Classifier: Programming Language :: Python :: 3
Classifier: Topic :: Software Development
Requires-Dist: pyparsing>=3.1.4
Project-URL: Homepage, https://github.com/maxyz/pyilpp
Project-URL: Issues, https://github.com/maxyz/pyilpp/issues
